LICENSE
MANIFEST.in
README.md
setup.py
geographnet/__init__.py
geographnet/traintest_pm.py
geographnet.egg-info/PKG-INFO
geographnet.egg-info/SOURCES.txt
geographnet.egg-info/dependency_links.txt
geographnet.egg-info/not-zip-safe
geographnet.egg-info/top_level.txt
geographnet/model/__init__.py
geographnet/model/geogcon.py
geographnet/model/geographpnet.py
geographnet/model/kddwei.py
geographnet/model/wdatasampling.py
geographnet/model/wsampler.py