Metadata-Version: 2.1
Name: geographnet
Version: 0.1.1
Summary: Library for Geographic Graph Hybrid Network
Home-page: https://github.com/lspatial/geographnet
Author: Lianfa Li
Author-email: lspatial@gmail.com
License: UNKNOWN
Platform: UNKNOWN
Classifier: Development Status :: 6 - Mature
Classifier: Intended Audience :: Science/Research
Classifier: License :: OSI Approved :: MIT License
Classifier: Programming Language :: Python :: 3
Classifier: Programming Language :: Python :: 3.3
Classifier: Programming Language :: Python :: 3.4
Classifier: Programming Language :: Python :: 3.5
Classifier: Programming Language :: Python :: 3.6
Classifier: Programming Language :: Python :: 3.7
